iproute4mac/__init__.py
iproute4mac/brfdb.py
iproute4mac/brlink.py
iproute4mac/data.py
iproute4mac/debug.py
iproute4mac/ifconfig.py
iproute4mac/ipaddress.py
iproute4mac/iplink.py
iproute4mac/iplink_bond.py
iproute4mac/iplink_bridge.py
iproute4mac/iplink_feth.py
iproute4mac/iplink_veth.py
iproute4mac/iplink_vlan.py
iproute4mac/ipneigh.py
iproute4mac/iproute.py
iproute4mac/libc.py
iproute4mac/nud.py
iproute4mac/prefix.py
iproute4mac/route.py
iproute4mac/socket.py
iproute4mac/utils.py
iproute4mac/cmd/bridge.py
iproute4mac/cmd/ip.py
iproute4mac-0.5.7.data/data/share/man/COPYING
iproute4mac-0.5.7.data/data/share/man/man8/bridge.8
iproute4mac-0.5.7.data/data/share/man/man8/ip-address.8
iproute4mac-0.5.7.data/data/share/man/man8/ip-link.8
iproute4mac-0.5.7.data/data/share/man/man8/ip-neighbour.8
iproute4mac-0.5.7.data/data/share/man/man8/ip-route.8
iproute4mac-0.5.7.data/data/share/man/man8/ip.8
iproute4mac-0.5.7.dist-info/AUTHORS
iproute4mac-0.5.7.dist-info/LICENSE
iproute4mac-0.5.7.dist-info/METADATA
iproute4mac-0.5.7.dist-info/WHEEL
iproute4mac-0.5.7.dist-info/entry_points.txt
iproute4mac-0.5.7.dist-info/pbr.json
iproute4mac-0.5.7.dist-info/top_level.txt
iproute4mac-0.5.7.dist-info/RECORD
