Metadata-Version: 2.1
Name: iproute4mac
Version: 0.5.7
Summary: iproute for Mac
Home-page: https://github.com/signal-09/iproute4mac
Author: Ettore Simone
Author-email: ettore.simone@gmail.com
License: Apache License, Version 2.0
Project-URL: Source, https://github.com/signal-09/iproute4mac
Project-URL: Bug Reports, https://github.com/signal-09/iproute4mac/issues
Keywords: iproute2, ip, ifconfig
Classifier: Development Status :: 4 - Beta
Classifier: Environment :: Console
Classifier: Intended Audience :: System Administrators
Classifier: License :: OSI Approved :: Apache Software License
Classifier: Operating System :: MacOS :: MacOS X
Classifier: Programming Language :: Python :: 3.10
Classifier: Topic :: System :: Networking
Requires-Python: >=3.10
License-File: LICENSE
License-File: AUTHORS
Requires-Dist: pbr !=2.1.0,>=2.0.0
